customselectwidget/__init__.py
customselectwidget/customselectwidget.py
django_customselectwidget-0.1.1.dist-info/LICENSE
django_customselectwidget-0.1.1.dist-info/METADATA
django_customselectwidget-0.1.1.dist-info/WHEEL
django_customselectwidget-0.1.1.dist-info/top_level.txt
django_customselectwidget-0.1.1.dist-info/RECORD
