Metadata-Version: 2.1
Name: django-customselectwidget
Version: 0.1.1
Summary: Django Custom select widget
Home-page: https://github.com/hisham2k9/django-customselectwidget
Author: Sayed Hisham
Author-email: hisham2k9@gmail.com
License: LGPL 3
Keywords: django,custom,select,field,choices,widget
Platform: UNKNOWN
Classifier: Framework :: Django
Classifier: License :: OSI Approved :: GNU Library or Lesser General Public License (LGPL)
Classifier: Operating System :: OS Independent
Classifier: Programming Language :: Python :: 3
License-File: LICENSE
Requires-Dist: django (>=2.0)
